create_django_project.py
create_djangoproject_script-2.0.dist-info/METADATA
create_djangoproject_script-2.0.dist-info/WHEEL
create_djangoproject_script-2.0.dist-info/entry_points.txt
create_djangoproject_script-2.0.dist-info/top_level.txt
create_djangoproject_script-2.0.dist-info/RECORD
